{
  "annotations": {
    "list": [
      {
        "builtIn": 1,
        "datasource": {
          "type": "grafana",
          "uid": "-- Grafana --"
        },
        "enable": true,
        "hide": true,
        "iconColor": "rgba(0, 211, 255, 1)",
        "name": "Annotations & Alerts",
        "type": "dashboard"
      }
    ]
  },
  "editable": true,
  "fiscalYearStartMonth": 0,
  "graphTooltip": 0,
  "id": 1,
  "links": [],
  "liveNow": true,
  "panels": [
    {
      "datasource": {
        "type": "postgres",
        "uid": "P41D990B0F3F3E8C1"
      },
      "fieldConfig": {
        "defaults": {
          "color": {
            "mode": "palette-classic"
          },
          "custom": {
            "axisBorderShow": false,
            "axisCenteredZero": false,
            "axisColorMode": "text",
            "axisLabel": "",
            "axisPlacement": "auto",
            "barAlignment": 0,
            "drawStyle": "line",
            "fillOpacity": 0,
            "gradientMode": "none",
            "hideFrom": {
              "legend": false,
              "tooltip": false,
              "viz": false
            },
            "insertNulls": false,
            "lineInterpolation": "linear",
            "lineWidth": 1,
            "pointSize": 5,
            "scaleDistribution": {
              "type": "linear"
            },
            "showPoints": "auto",
            "spanNulls": false,
            "stacking": {
              "group": "A",
              "mode": "none"
            },
            "thresholdsStyle": {
              "mode": "off"
            }
          },
          "mappings": [],
          "thresholds": {
            "mode": "absolute",
            "steps": [
              {
                "color": "green",
                "value": null
              },
              {
                "color": "red",
                "value": 80
              }
            ]
          }
        },
        "overrides": []
      },
      "gridPos": {
        "h": 14,
        "w": 16,
        "x": 0,
        "y": 0
      },
      "id": 1,
      "options": {
        "legend": {
          "calcs": [],
          "displayMode": "list",
          "placement": "bottom",
          "showLegend": true
        },
        "tooltip": {
          "mode": "single",
          "sort": "none"
        }
      },
      "targets": [
        {
          "datasource": {
            "type": "postgres",
            "uid": "P41D990B0F3F3E8C1"
          },
          "editorMode": "code",
          "format": "time_series",
          "rawQuery": true,
          "rawSql": "SELECT\n  time AS \"time\",\n  open,\n  high,\n  low,\n  close\nFROM aggregates\nWHERE\n  $__timeFilter(time) AND symbol = '$symbol' AND window_sec = $window_sec\nORDER BY time",
          "refId": "A",
          "sql": {
            "columns": [
              {
                "parameters": [],
                "type": "function"
              }
            ],
            "groupBy": [
              {
                "property": {
                  "type": "string"
                },
                "type": "groupBy"
              }
            ],
            "limit": 50
          }
        },
        {
          "datasource": {
            "type": "postgres",
            "uid": "P41D990B0F3F3E8C1"
          },
          "editorMode": "code",
          "format": "time_series",
          "hide": false,
          "rawQuery": true,
          "rawSql": "SELECT\n  time AS \"time\",\n  vwap\nFROM aggregates\nWHERE\n  $__timeFilter(time) AND symbol = '$symbol' AND window_sec = $window_sec\nORDER BY time",
          "refId": "B",
          "sql": {
            "columns": [
              {
                "parameters": [],
                "type": "function"
              }
            ],
            "groupBy": [
              {
                "property": {
                  "type": "string"
                },
                "type": "groupBy"
              }
            ],
            "limit": 50
          }
        }
      ],
      "title": "$symbol Candlesticks & VWAP",
      "type": "candlestick"
    },
    {
      "datasource": {
        "type": "postgres",
        "uid": "P41D990B0F3F3E8C1"
      },
      "fieldConfig": {
        "defaults": {
          "color": {
            "mode": "thresholds"
          },
          "custom": {
            "align": "auto",
            "cellOptions": {
              "type": "auto"
            },
            "inspect": false
          },
          "mappings": [],
          "thresholds": {
            "mode": "absolute",
            "steps": [
              {
                "color": "green",
                "value": null
              },
              {
                "color": "red",
                "value": 80
              }
            ]
          }
        },
        "overrides": [
          {
            "matcher": {
              "id": "byName",
              "options": "severity"
            },
            "properties": [
              {
                "id": "custom.cellOptions",
                "value": {
                  "mode": "color-background",
                  "type": "color-text"
                }
              },
              {
                "id": "thresholds",
                "value": {
                  "mode": "absolute",
                  "steps": [
                    {
                      "color": "blue",
                      "value": null
                    },
                    {
                      "color": "yellow",
                      "value": 1
                    },
                    {
                      "color": "red",
                      "value": 2
                    }
                  ]
                }
              },
              {
                "id": "mappings",
                "value": [
                  {
                    "options": {
                      "high": {
                        "color": "red",
                        "index": 2,
                        "text": "HIGH"
                      },
                      "low": {
                        "color": "blue",
                        "index": 0,
                        "text": "LOW"
                      },
                      "medium": {
                        "color": "yellow",
                        "index": 1,
                        "text": "MEDIUM"
                      }
                    },
                    "type": "value"
                  }
                ]
              }
            ]
          }
        ]
      },
      "gridPos": {
        "h": 14,
        "w": 8,
        "x": 16,
        "y": 0
      },
      "id": 2,
      "options": {
        "cellHeight": "sm",
        "footer": {
          "countRows": false,
          "fields": "",
          "reducer": [
            "sum"
          ],
          "show": false
        },
        "showHeader": true,
        "sortBy": [
          {
            "desc": true,
            "displayName": "Time"
          }
        ]
      },
      "pluginVersion": "10.4.0",
      "targets": [
        {
          "datasource": {
            "type": "postgres",
            "uid": "P41D990B0F3F3E8C1"
          },
          "editorMode": "code",
          "format": "table",
          "rawQuery": true,
          "rawSql": "SELECT\n  time AS \"Time\",\n  symbol AS \"Symbol\",\n  alert_type AS \"Type\",\n  severity AS \"Severity\",\n  message AS \"Message\",\n  trigger_price AS \"Price\"\nFROM alerts\nWHERE\n  $__timeFilter(time) AND ('$symbol' = 'ALL' OR symbol = '$symbol')\nORDER BY time DESC\nLIMIT 50",
          "refId": "A",
          "sql": {
            "columns": [
              {
                "parameters": [],
                "type": "function"
              }
            ],
            "groupBy": [
              {
                "property": {
                  "type": "string"
                },
                "type": "groupBy"
              }
            ],
            "limit": 50
          }
        }
      ],
      "title": "Recent Alerts",
      "type": "table"
    }
  ],
  "refresh": "5s",
  "schemaVersion": 39,
  "tags": [
    "stockmarket"
  ],
  "templating": {
    "list": [
      {
        "current": {
          "selected": true,
          "text": "AAPL",
          "value": "AAPL"
        },
        "hide": 0,
        "includeAll": true,
        "multi": false,
        "name": "symbol",
        "options": [
          {
            "selected": true,
            "text": "AAPL",
            "value": "AAPL"
          },
          {
            "selected": false,
            "text": "MSFT",
            "value": "MSFT"
          },
          {
            "selected": false,
            "text": "GOOGL",
            "value": "GOOGL"
          },
          {
            "selected": false,
            "text": "NVDA",
            "value": "NVDA"
          }
        ],
        "query": "AAPL, MSFT, GOOGL, AMZN, NVDA, TSLA, META, JPM, SPY, QQQ",
        "queryValue": "",
        "skipUrlSync": false,
        "type": "custom"
      },
      {
        "current": {
          "selected": true,
          "text": "1 Min (60s)",
          "value": "60"
        },
        "hide": 0,
        "includeAll": false,
        "multi": false,
        "name": "window_sec",
        "options": [
          {
            "selected": true,
            "text": "1 Min (60s)",
            "value": "60"
          },
          {
            "selected": false,
            "text": "5 Min (300s)",
            "value": "300"
          },
          {
            "selected": false,
            "text": "15 Min (900s)",
            "value": "900"
          }
        ],
        "query": "60 : 1 Min (60s), 300 : 5 Min (300s), 900 : 15 Min (900s)",
        "queryValue": "",
        "skipUrlSync": false,
        "type": "custom"
      }
    ]
  },
  "time": {
    "from": "now-1h",
    "to": "now"
  },
  "timepicker": {},
  "timezone": "browser",
  "title": "Live Market Dashboard",
  "uid": "db9b21f3-231a-4c27-a0e2-82390a827407",
  "version": 1
}
